[{"Title":"Slacker","Genre":"Comedy|Drama","Cast":"Fields Oulner","Year":2012},
{"Title":"Guarding Tess","Genre":"Comedy|Drama","Cast":"Der Renvoise","Year":2003},
{"Title":"Men Without Women","Genre":"Action|Drama","Cast":"Felix Marcone","Year":2011},
{"Title":"Separate Tables","Genre":"Drama","Cast":"Renell Mordecai","Year":1993},
{"Title":"Shaggy Dog, The","Genre":"Adventure|Children|Comedy|Fantasy","Cast":"Emmie Rosbottom","Year":2004},
{"Title":"My Fair Lady","Genre":"Comedy|Drama|Musical|Romance","Cast":"Charlotta Burlingame","Year":2008},
{"Title":"Land Ho!","Genre":"Adventure|Comedy|Drama","Cast":"Binny Grzeszczyk","Year":1998},
{"Title":"Here Comes the Groom","Genre":"Comedy|Musical|Romance","Cast":"Terrell Samarth","Year":2010},
{"Title":"Steamroller and the Violin, The (Katok i skripka)","Genre":"Drama","Cast":"Rosetta Valens-Smith","Year":2011},
{"Title":"Urban Menace","Genre":"Action|Horror","Cast":"Felike Aasaf","Year":2012},
{"Title":"Eagle Eye","Genre":"Action|Crime|Thriller|IMAX","Cast":"Renate Lambertini","Year":1992},
{"Title":"Breaker! Breaker!","Genre":"Action|Adventure|Crime","Cast":"Vittoria Arnell","Year":1997},
{"Title":"How to Make Money Selling Drugs","Genre":"Documentary","Cast":"Maryanne Woolfitt","Year":2013},
{"Title":"Craigslist Killer, The ","Genre":"Crime|Drama|Thriller","Cast":"Killy Tomaszek","Year":1998},
{"Title":"Hannah Free","Genre":"Drama","Cast":"Eleonore Braznell","Year":1991},
{"Title":"Frozen Ground, The","Genre":"Crime|Drama|Thriller","Cast":"Juline Filipczak","Year":1997},
{"Title":"Mommy","Genre":"Drama","Cast":"Win Grundell","Year":1966},
{"Title":"Little Lord Fauntleroy","Genre":"Children|Drama|Romance","Cast":"Willard Harrison","Year":1998},
{"Title":"Taming of the Shrew, The","Genre":"Comedy","Cast":"Tann Beller","Year":1990},
{"Title":"Baxter","Genre":"Drama|Horror","Cast":"Reube Hargroves","Year":1994},
{"Title":"Dracula","Genre":"Horror|Romance","Cast":"Noni Burgne","Year":1999},
{"Title":"Asylum","Genre":"Horror|Thriller","Cast":"Randy Benge","Year":2002},
{"Title":"Last of the Mohicans, The","Genre":"Action|Romance|War|Western","Cast":"Milly Upcott","Year":1995},
{"Title":"Motocrossed","Genre":"Action|Children|Comedy|Romance","Cast":"Gualterio Beglin","Year":2004},
{"Title":"Uncle Buck","Genre":"Comedy","Cast":"Duke Chastagnier","Year":2010},
{"Title":"Kull the Conqueror","Genre":"Action|Adventure","Cast":"Cristobal Cressor","Year":2009},
{"Title":"ID:A","Genre":"Crime|Thriller","Cast":"Felicity Timmis","Year":2008},
{"Title":"Election Day","Genre":"Documentary","Cast":"Boote Mate","Year":2004},
{"Title":"Phantom of the Rue Morgue","Genre":"Crime|Horror|Mystery","Cast":"Cassandra Shorrock","Year":1987},
{"Title":"Five and Ten","Genre":"Romance","Cast":"Charlene Brooke","Year":1988},
{"Title":"What Did the Lady Forget? (Shukujo wa nani o wasureta ka) ","Genre":"Comedy|Drama","Cast":"Robb Wigg","Year":2008},
{"Title":"The Very Thought of You","Genre":"Drama|Romance","Cast":"Amelia Jaquemar","Year":2012},
{"Title":"The Sword and the Rose","Genre":"Adventure|Children|Drama","Cast":"Buckie Cundict","Year":2003},
{"Title":"Benny Goodman Story, The","Genre":"Drama|Musical","Cast":"Ron Buglar","Year":2006},
{"Title":"Proxy","Genre":"Drama|Horror|Thriller","Cast":"Elora Giuron","Year":1996},
{"Title":"Near Dark","Genre":"Horror|Western","Cast":"Sid Scotchmor","Year":2008},
{"Title":"Roula","Genre":"Drama","Cast":"Bartholomeo Doree","Year":2003},
{"Title":"Paisan (Paisà)","Genre":"Drama|War","Cast":"Collete Maynard","Year":2010},
{"Title":"Accidental Golfer, The (Den ofrivillige golfaren)","Genre":"Comedy","Cast":"Vaughan Greneham","Year":2010},
{"Title":"How to Cook Your Life","Genre":"Documentary","Cast":"Leo Ingrem","Year":1995},
{"Title":"Street Fighter II: The Animated Movie (Sutorîto Faitâ II gekijô-ban)","Genre":"Action|Animation","Cast":"Renado Bertin","Year":2005},
{"Title":"Prayers for Bobby","Genre":"Drama","Cast":"Roslyn Mordie","Year":1992},
{"Title":"The Magic Crystal","Genre":"Adventure|Animation|Children|Comedy|Fantasy","Cast":"Simone Warman","Year":2008},
{"Title":"Swell Season, The","Genre":"Documentary|Romance","Cast":"Issi Talman","Year":2009},
{"Title":"One Crazy Summer","Genre":"Comedy","Cast":"Cornela Morford","Year":1990},
{"Title":"Passage to Marseille","Genre":"Adventure|Drama|War","Cast":"Shayna Toomey","Year":2001},
{"Title":"Ronin","Genre":"Action|Crime|Thriller","Cast":"Gui Manneville","Year":2010},
{"Title":"Gracie's Choice","Genre":"Drama","Cast":"Babbie Tidbold","Year":2009},
{"Title":"Mortician, The","Genre":"Thriller","Cast":"Lorenza Iddison","Year":2009},
{"Title":"On the Occasion of Remembering the Turning Gate (Saenghwalui balgyeon)","Genre":"Drama","Cast":"Hurley Condell","Year":2004}]